normalisr/__init__.py
normalisr/__main__.py
normalisr/association.py
normalisr/binnet.py
normalisr/coex.py
normalisr/de.py
normalisr/gocovt.py
normalisr/lcpm.py
normalisr/norm.py
normalisr/normalisr.py
normalisr/parallel.py
normalisr/qc.py
normalisr/run.py
normalisr-1.0.0.data/scripts/normalisr
normalisr-1.0.0.dist-info/LICENSE
normalisr-1.0.0.dist-info/METADATA
normalisr-1.0.0.dist-info/WHEEL
normalisr-1.0.0.dist-info/top_level.txt
normalisr-1.0.0.dist-info/RECORD
