Metadata-Version: 2.1
Name: normalisr
Version: 1.0.0
Summary: Normalisr Offers Robust Modelling of Associations Linearly In Single-cell RNA-seq
Home-page: https://github.com/lingfeiwang/normalisr
Author: Lingfei Wang
Author-email: Lingfei.Wang.github@outlook.com
License: BSD-3-Clause
Platform: UNKNOWN
Classifier: Development Status :: 5 - Production/Stable
Classifier: License :: OSI Approved :: BSD License
Classifier: Environment :: Console
Classifier: Intended Audience :: Science/Research
Classifier: Intended Audience :: Developers
Classifier: Operating System :: OS Independent
Classifier: Programming Language :: Python :: 3
Classifier: Topic :: Scientific/Engineering :: Bio-Informatics
License-File: LICENSE
Requires-Dist: numpy
Requires-Dist: scipy
Requires-Dist: pandas
Requires-Dist: scikit-learn
Requires-Dist: biothings-client
Requires-Dist: goatools (>=0.7.11)
